fake_geo_images/__init__.py
fake_geo_images/fakegeoimages.py
fake_geo_images/logging.py
fake_geo_images/raster.py
fake_geo_images/test/__init__.py
fake_geo_images/test/test_fakegeoimages.py
fake_geo_images-0.1.5.dist-info/LICENSE
fake_geo_images-0.1.5.dist-info/METADATA
fake_geo_images-0.1.5.dist-info/WHEEL
fake_geo_images-0.1.5.dist-info/top_level.txt
fake_geo_images-0.1.5.dist-info/RECORD
