Metadata-Version: 2.1
Name: fake-geo-images
Version: 0.1.5
Summary: Fake geospatial images for unit tests
Home-page: https://github.com/up42/fake-geo-images
Author: UP42
Author-email: support@up42.com
License: MIT
Classifier: Programming Language :: Python :: 3
Classifier: License :: OSI Approved :: MIT License
Classifier: Operating System :: OS Independent
Classifier: Development Status :: 4 - Beta
Classifier: Intended Audience :: Developers
Requires-Python: >=3.6
License-File: LICENSE
Requires-Dist: numpy >=1.26.3
Requires-Dist: scipy >=1.11.4
Requires-Dist: rasterio >=1.3.9
Requires-Dist: scikit-image >=0.22.0
Requires-Dist: rio-cogeo >=5.1.1
